{
    "$schema": "https://cloud.uipath.com/draft/2024-12/entry-point",
    "$id": "entry-points.json",
    "entryPoints": [
        {
            "filePath": "agent",
            "uniqueId": "b5df581b-656c-4a1c-907b-b04271485cf1",
            "type": "agent",
            "input": {
                "type": "object",
                "properties": {
                    "query": {
                        "title": "Query",
                        "type": "string"
                    }
                },
                "required": [
                    "query"
                ]
            },
            "output": {
                "type": "object",
                "properties": {
                    "response": {
                        "default": null,
                        "title": "Response",
                        "type": "string"
                    }
                },
                "required": []
            },
            "graph": {
                "nodes": [
                    {
                        "id": "__start__",
                        "name": "__start__",
                        "type": "__start__",
                        "subgraph": null,
                        "metadata": {}
                    },
                    {
                        "id": "initialize",
                        "name": "initialize",
                        "type": "node",
                        "subgraph": null,
                        "metadata": {}
                    },
                    {
                        "id": "retrieve",
                        "name": "retrieve",
                        "type": "node",
                        "subgraph": null,
                        "metadata": {}
                    },
                    {
                        "id": "generate_query_or_respond",
                        "name": "generate_query_or_respond",
                        "type": "node",
                        "subgraph": null,
                        "metadata": {}
                    },
                    {
                        "id": "rewrite_question",
                        "name": "rewrite_question",
                        "type": "node",
                        "subgraph": null,
                        "metadata": {}
                    },
                    {
                        "id": "generate_answer",
                        "name": "generate_answer",
                        "type": "node",
                        "subgraph": null,
                        "metadata": {}
                    },
                    {
                        "id": "output",
                        "name": "output",
                        "type": "node",
                        "subgraph": null,
                        "metadata": {}
                    },
                    {
                        "id": "__end__",
                        "name": "__end__",
                        "type": "__end__",
                        "subgraph": null,
                        "metadata": {}
                    }
                ],
                "edges": [
                    {
                        "source": "__start__",
                        "target": "initialize",
                        "label": null
                    },
                    {
                        "source": "generate_answer",
                        "target": "output",
                        "label": null
                    },
                    {
                        "source": "generate_query_or_respond",
                        "target": "output",
                        "label": "__end__"
                    },
                    {
                        "source": "generate_query_or_respond",
                        "target": "retrieve",
                        "label": "tools"
                    },
                    {
                        "source": "initialize",
                        "target": "generate_query_or_respond",
                        "label": null
                    },
                    {
                        "source": "retrieve",
                        "target": "generate_answer",
                        "label": null
                    },
                    {
                        "source": "retrieve",
                        "target": "rewrite_question",
                        "label": null
                    },
                    {
                        "source": "rewrite_question",
                        "target": "generate_query_or_respond",
                        "label": null
                    },
                    {
                        "source": "output",
                        "target": "__end__",
                        "label": null
                    }
                ]
            }
        }
    ]
}